pargv.py
pargv-0.2.0.dist-info/METADATA
pargv-0.2.0.dist-info/WHEEL
pargv-0.2.0.dist-info/top_level.txt
pargv-0.2.0.dist-info/RECORD
