Metadata-Version: 2.1
Name: pargv
Version: 0.2.0
Summary: Parse command line arguments into a list of args and a dict of kwargs.
Home-page: UNKNOWN
License: UNKNOWN
Platform: UNKNOWN
Provides-Extra: dev
Requires-Dist: pytest ; extra == 'dev'
